unstar_pipfile/__init__.py
unstar_pipfile/__main__.py
unstar_pipfile/unstar_pipfile.py
unstar_pipfile-0.2.0.dist-info/entry_points.txt
unstar_pipfile-0.2.0.dist-info/WHEEL
unstar_pipfile-0.2.0.dist-info/METADATA
unstar_pipfile-0.2.0.dist-info/RECORD
